zaphodvox/__init__.py
zaphodvox/audio.py
zaphodvox/encoder.py
zaphodvox/main.py
zaphodvox/manifest.py
zaphodvox/named_voices.py
zaphodvox/parser.py
zaphodvox/progress.py
zaphodvox/text.py
zaphodvox/voice.py
zaphodvox/elevenlabs/__init__.py
zaphodvox/elevenlabs/encoder.py
zaphodvox/elevenlabs/voice.py
zaphodvox/googlecloud/__init__.py
zaphodvox/googlecloud/encoder.py
zaphodvox/googlecloud/voice.py
zaphodvox-1.2.0.dist-info/METADATA
zaphodvox-1.2.0.dist-info/WHEEL
zaphodvox-1.2.0.dist-info/entry_points.txt
zaphodvox-1.2.0.dist-info/licenses/LICENSE
zaphodvox-1.2.0.dist-info/RECORD
