Metadata-Version: 2.1
Name: zaphodvox
Version: 1.2.0
Summary: A command-line interface and python library for encoding text into synthetic speech using Google Cloud Text-To-Speech or ElevenLabs APIs.
Project-URL: Homepage, https://github.com/gumptionthomas/zaphodvox
Project-URL: Source, https://github.com/gumptionthomas/zaphodvox
Project-URL: Tracker, https://github.com/gumptionthomas/zaphodvox/issues
Author-email: Thomas Bohmbach Jr <thomasbohmbach@gmail.com>
License-Expression: MIT
License-File: LICENSE
Keywords: audio,elevenlabs,google-cloud-texttospeech,mp3,ogg,text-to-speech,tts,wav
Classifier: Development Status :: 5 - Production/Stable
Classifier: Environment :: Console
Classifier: Framework :: Pydantic
Classifier: License :: OSI Approved :: MIT License
Classifier: Operating System :: OS Independent
Classifier: Programming Language :: Python :: 3 :: Only
Classifier: Topic :: Multimedia :: Sound/Audio :: Sound Synthesis
Classifier: Topic :: Multimedia :: Sound/Audio :: Speech
Classifier: Topic :: Text Processing
Requires-Python: >=3.10
Requires-Dist: elevenlabs==0.2.27
Requires-Dist: google-cloud-texttospeech==2.15.1
Requires-Dist: pydantic==2.5.3
Requires-Dist: pydub==0.25.1
Requires-Dist: rich==13.7.0
Requires-Dist: tenacity==8.2.3
Requires-Dist: unidecode==1.3.8
